django_firestore_session_engine/__init__.py
django_firestore_session_engine/apps.py
django_firestore_session_engine/cfg.py
django_firestore_session_engine/engine.py
django_firestore_session_engine-1.1.dist-info/METADATA
django_firestore_session_engine-1.1.dist-info/WHEEL
django_firestore_session_engine-1.1.dist-info/licenses/LICENSE
django_firestore_session_engine-1.1.dist-info/RECORD
