Metadata-Version: 2.3
Name: django_firestore_session_engine
Version: 1.1
Summary: This is a simple Django Session Engine that uses Firestore as the database to store session data.
Project-URL: Homepage, https://github.com/resun-c/django-firestore-session-engine
Project-URL: Issues, https://github.com/resun-c/django-firestore-session-engine/issues
Author-email: _resun <resun.saif@gmail.com>
License-File: LICENSE
Classifier: License :: OSI Approved :: MIT License
Classifier: Operating System :: OS Independent
Classifier: Programming Language :: Python :: 3
Requires-Python: >=3.8
